{
  "type": "FeatureCollection",
  "crs": {
    "type": "name",
    "properties": { "name": "urn:ogc:def:crs:OGC:1.3:CRS84" }
  },
  "features": [
    {
      "type": "Feature",
      "properties": {
        "type": "dpw",
        "quote": "None",
        "datetime_string": "Nov. 30 10 a.m.",
        "date": "nov30",
        "time_bucket": "10am-noon"
      },
      "geometry": {
        "type": "Point",
        "coordinates": [-122.41830267858859, 37.75250664354318]
      }
    },
    {
      "type": "Feature",
      "properties": {
        "type": "dpw",
        "quote": "None",
        "datetime_string": "Nov. 30 10 a.m.",
        "date": "nov30",
        "time_bucket": "10am-noon"
      },
      "geometry": {
        "type": "Point",
        "coordinates": [-122.41832444756878, 37.752455790117544]
      }
    },
    {
      "type": "Feature",
      "properties": {
        "type": "dpw",
        "quote": "None",
        "datetime_string": "Nov. 30 10 a.m.",
        "date": "nov30",
        "time_bucket": "10am-noon"
      },
      "geometry": {
        "type": "Point",
        "coordinates": [-122.41828882560121, 37.752455007756865]
      }
    },
    {
      "type": "Feature",
      "properties": {
        "type": "dpw",
        "quote": "None",
        "datetime_string": "Nov. 30 2 p.m.",
        "date": "nov30",
        "time_bucket": "noon-2pm"
      },
      "geometry": {
        "type": "Point",
        "coordinates": [-122.4182482561381, 37.75242371332339]
      }
    },
    {
      "type": "Feature",
      "properties": {
        "type": "dpw",
        "quote": "None",
        "datetime_string": "Nov. 30 2 p.m.",
        "date": "nov30",
        "time_bucket": "noon-2pm"
      },
      "geometry": {
        "type": "Point",
        "coordinates": [-122.4182522141345, 37.75253167906298]
      }
    },
    {
      "type": "Feature",
      "properties": {
        "type": "police",
        "quote": "None",
        "datetime_string": "Nov. 30 10 a.m.",
        "date": "nov30",
        "time_bucket": "10am-noon"
      },
      "geometry": {
        "type": "Point",
        "coordinates": [-122.41835116404447, 37.75239163651533]
      }
    },
    {
      "type": "Feature",
      "properties": {
        "type": "police",
        "quote": "None",
        "datetime_string": "Nov. 30 10 a.m.",
        "date": "nov30",
        "time_bucket": "10am-noon"
      },
      "geometry": {
        "type": "Point",
        "coordinates": [-122.41829575209489, 37.75234547718178]
      }
    },
    {
      "type": "Feature",
      "properties": {
        "type": "police",
        "quote": "None",
        "datetime_string": "Nov. 30 2 p.m.",
        "date": "nov30",
        "time_bucket": "noon-2pm"
      },
      "geometry": {
        "type": "Point",
        "coordinates": [-122.41829773109309, 37.75240415429574]
      }
    },
    {
      "type": "Feature",
      "properties": {
        "type": "police",
        "quote": "None",
        "datetime_string": "Nov. 30 2 p.m.",
        "date": "nov30",
        "time_bucket": "noon-2pm"
      },
      "geometry": {
        "type": "Point",
        "coordinates": [-122.41835809053816, 37.75246126664199]
      }
    },
    {
      "type": "Feature",
      "properties": {
        "type": "vendor",
        "quote": "Just a pair of white sneakers.",
        "datetime_string": "Nov. 30 2 p.m.",
        "date": "nov30",
        "time_bucket": "2-4pm"
      },
      "geometry": {
        "type": "Point",
        "coordinates": [-122.41842802717665, 37.75292351080011]
      }
    }
  ]
}
